autoD/__init__.py
autoD-3.7.0.dist-info/LICENSE
autoD-3.7.0.dist-info/METADATA
autoD-3.7.0.dist-info/WHEEL
autoD-3.7.0.dist-info/top_level.txt
autoD-3.7.0.dist-info/RECORD
