Metadata-Version: 2.1
Name: autoD
Version: 3.7.0
Summary: A light-weight forward auto differentiation package
Home-page: https://github.com/WeiXuanChan/autoD
Author: Wei Xuan, Chan
Author-email: w.x.chan1986@gmail.com
License: MIT
Download-URL: https://github.com/WeiXuanChan/autoD/archive/v3.7.0.tar.gz
Keywords: differentiate,auto,forward
Platform: UNKNOWN
Classifier: Development Status :: 5 - Production/Stable
Classifier: Intended Audience :: Developers
Classifier: Topic :: Software Development :: Build Tools
Classifier: License :: OSI Approved :: MIT License
Classifier: Programming Language :: Python :: 3
Classifier: Programming Language :: Python :: 3.3
Classifier: Programming Language :: Python :: 3.4
Classifier: Programming Language :: Python :: 3.5
Classifier: Programming Language :: Python :: 3.6
